atsphinx/typst/__init__.py
atsphinx/typst/builders.py
atsphinx/typst/config.py
atsphinx/typst/py.typed
atsphinx/typst/theming.py
atsphinx/typst/writer.py
atsphinx/typst/elements/__init__.py
atsphinx/typst/elements/_templating.py
atsphinx/typst/elements/base.py
atsphinx/typst/elements/foundations.py
atsphinx/typst/elements/model.py
atsphinx/typst/elements/text.py
atsphinx/typst/elements/visualize.py
atsphinx/typst/elements/custom/__init__.py
atsphinx/typst/elements/custom/docutils.py
atsphinx/typst/themes/basic/document.typ.jinja
atsphinx/typst/themes/basic/theme.toml
atsphinx/typst/themes/basic/assets/docutils.typ
atsphinx/typst/themes/manual/document.typ.jinja
atsphinx/typst/themes/manual/theme.toml
atsphinx_typst-0.0.5.dist-info/METADATA
atsphinx_typst-0.0.5.dist-info/WHEEL
atsphinx_typst-0.0.5.dist-info/entry_points.txt
atsphinx_typst-0.0.5.dist-info/licenses/LICENSE
atsphinx_typst-0.0.5.dist-info/RECORD
